edf_plasma_cli/__init__.py
edf_plasma_cli/__version__.py
edf_plasma_cli/main.py
edf_plasma_cli/command/__init__.py
edf_plasma_cli/command/abc.py
edf_plasma_cli/command/dissect.py
edf_plasma_cli/command/list.py
edf_plasma_cli-1.0.0.dist-info/licenses/LICENSE
edf_plasma_cli-1.0.0.dist-info/METADATA
edf_plasma_cli-1.0.0.dist-info/WHEEL
edf_plasma_cli-1.0.0.dist-info/entry_points.txt
edf_plasma_cli-1.0.0.dist-info/top_level.txt
edf_plasma_cli-1.0.0.dist-info/RECORD
